[
    {
        "id": 1,
        "title": "App Android - To do List",
        "description": "Application, developed with React Native, that performs a simple CRUD of a to-do list using Firebase.",
        "technologies": [
            {
                "name": "TbBrandJavascript",
                "id": "tb",
                "backgroundColor": "#f0db4f"
            },
            {
                "name": "GrNode",
                "id": "gr",
                "backgroundColor": "#68a063"
            },
            {
                "name": "FaReact",
                "id": "fa",
                "backgroundColor": "#61DBFB"
            },
            {
                "name": "BiLogoFirebase",
                "id": "bi",
                "backgroundColor": "#FFA611"
            }
        ]
    },
    {
        "id": 2,
        "title": "App Android - To do List",
        "description": "Application, developed with React Native, that performs a simple CRUD of a to-do list using Firebase.",
        "technologies": [
            {
                "name": "TbBrandJavascript",
                "id": "tb",
                "backgroundColor": "#f0db4f"
            },
            {
                "name": "GrNode",
                "id": "gr",
                "backgroundColor": "#68a063"
            },
            {
                "name": "FaReact",
                "id": "fa",
                "backgroundColor": "#61DBFB"
            },
            {
                "name": "BiLogoFirebase",
                "id": "bi",
                "backgroundColor": "#FFA611"
            }
        ]
    },
    {
        "id": 3,
        "title": "App Android - To do List",
        "description": "Application, developed with React Native, that performs a simple CRUD of a to-do list using Firebase.",
        "technologies": [
            {
                "name": "TbBrandJavascript",
                "id": "tb",
                "backgroundColor": "#f0db4f"
            },
            {
                "name": "GrNode",
                "id": "gr",
                "backgroundColor": "#68a063"
            },
            {
                "name": "FaReact",
                "id": "fa",
                "backgroundColor": "#61DBFB"
            },
            {
                "name": "BiLogoFirebase",
                "id": "bi",
                "backgroundColor": "#FFA611"
            }
        ]
    },
    {
        "id": 4,
        "title": "App Android - To do List",
        "description": "Application, developed with React Native, that performs a simple CRUD of a to-do list using Firebase.",
        "technologies": [
            {
                "name": "TbBrandJavascript",
                "id": "tb",
                "backgroundColor": "#f0db4f"
            },
            {
                "name": "GrNode",
                "id": "gr",
                "backgroundColor": "#68a063"
            },
            {
                "name": "FaReact",
                "id": "fa",
                "backgroundColor": "#61DBFB"
            },
            {
                "name": "BiLogoFirebase",
                "id": "bi",
                "backgroundColor": "#FFA611"
            }
        ]
    }
]